README
dragon.py
setup.py
dragonpy.egg-info/PKG-INFO
dragonpy.egg-info/SOURCES.txt
dragonpy.egg-info/dependency_links.txt
dragonpy.egg-info/top_level.txt