Metadata-Version: 1.0
Name: dragonpy
Version: 0.0.1
Summary: Dragonpay Python library
Home-page: https://github.com/jpanganiban/dragonpy.git
Author: Jesse Panganiban
Author-email: me@jpanganiban.com
License: UNKNOWN
Platform: UNKNOWN
